Metadata-Version: 2.1
Name: python-damas
Version: 1.0.2
Summary: Uma biblioteca do jogo de damas.
Home-page: https://github.com/ghurone/python-damas
Author: Erick Ghuron
Author-email: ghuron@usp.br
License: MIT
Keywords: damas jogo ghuron
Platform: UNKNOWN
Classifier: Development Status :: 1 - Planning
Classifier: License :: OSI Approved :: MIT License
Classifier: Natural Language :: Portuguese (Brazilian)
Classifier: Operating System :: OS Independent
Classifier: Topic :: Games/Entertainment :: Board Games
